DESCRIPTION.rst
MANIFEST.in
README.md
RELEASE-VERSION
setup.cfg
setup.py
version.py
serial_device2/__init__.py
serial_device2/serial_device2.py
serial_device2.egg-info/PKG-INFO
serial_device2.egg-info/SOURCES.txt
serial_device2.egg-info/dependency_links.txt
serial_device2.egg-info/requires.txt
serial_device2.egg-info/top_level.txt