Metadata-Version: 1.1
Name: serial_device2
Version: 1.4
Summary: Extends serial.Serial to add methods such as auto discovery of available serial ports in Linux, Windows, and Mac OS X
Home-page: https://github.com/janelia-pypi/serial_device_python
Author: Peter Polidoro
Author-email: polidorop@janelia.hhmi.org
License: BSD
Keywords: serial
Platform: UNKNOWN
Classifier: Development Status :: 4 - Beta
Classifier: Intended Audience :: Developers
Classifier: Topic :: Software Development :: Build Tools
Classifier: License :: OSI Approved :: BSD License
Classifier: Programming Language :: Python :: 2.7
